easyschedule/__init__.py
easyschedule/cron.py
easyschedule/scheduler.py
easyschedule-0.106.dist-info/LICENSE.MD
easyschedule-0.106.dist-info/METADATA
easyschedule-0.106.dist-info/WHEEL
easyschedule-0.106.dist-info/top_level.txt
easyschedule-0.106.dist-info/RECORD
