Metadata-Version: 2.1
Name: easyschedule
Version: 0.106
Summary: Easily schedule single or recurring sync/async tasks
Home-page: https://github.com/codemation/easyschedule
Author: Joshua Jamison
Author-email: joshjamison1@gmail.com
License: UNKNOWN
Platform: UNKNOWN
Classifier: Programming Language :: Python :: 3
Classifier: License :: OSI Approved :: MIT License
Classifier: Operating System :: OS Independent
Requires-Python: >=3.7, <4
